setup.py
shellout.py
shellout.egg-info/PKG-INFO
shellout.egg-info/SOURCES.txt
shellout.egg-info/dependency_links.txt
shellout.egg-info/top_level.txt