Metadata-Version: 1.0
Name: shellout
Version: 0.1
Summary:  Make your shelled out calls look like genuine OO code
Home-page: http://github.com/jbowes/shellout/
Author: James Bowes
Author-email: jbowes@dangerouslyinc.com
License: BSD
Platform: any
